{
    "books": [
      {
        "title": "ORANŽINIS ROMANAS",
        "body": "Ambasadoriaus užrašai apie Ukrainą, kuri jau niekada nebebus tokia pati, ir apie ukrainiečius, kurie gins kiekvieną savo žemės pėdą",
        "author": "Algirdas Kumža",
        "id": 1
      },
      {
        "title": "MAŽAS GYVENIMAS",
        "body": "viena labiausiai pritrenkiančių, metančių iššūkį, liūdinančių, sukrečiančių ir jaudinančių kelionių per sudėtingą žmogaus gyvenimą",
        "author": "Hanya Yanagihara",
        "id": 2
      },
      {
        "title": "OLIVIJA KITERIDŽ",
        "body": "Pulitzerio premija įvertinta ir „Emmy“ statulėlėmis apdovanotą serialą įkvėpusi knyga - negailestingai atviras žvilgsnis į žmogaus gyvenimo esmę",
        "author": "Elizabeth Strout",
        "id": 3
      },
      {
        "title": "GALIME IŠTRINTI",
        "body": "ČIA TESTUOJAM DRĄSIAI",
        "author": "JS ŽMONĖS",
        "id": 4
      },
      {
        "title": "Full React Tutorial",
        "body": "Hey gang, in this complete modern React tutorial we'll learn about React from the ground up - setup, JSX templates, components & events. We'll cover state & the use of hooks, the React Router & also how to handle asynchronous code in components.",
        "author": " The Net Ninja",
        "id": 5
      }
    ]
  }